undi/__init__.py
undi/undi.py
undi-1.0.dist-info/LICENSE
undi-1.0.dist-info/METADATA
undi-1.0.dist-info/WHEEL
undi-1.0.dist-info/top_level.txt
undi-1.0.dist-info/RECORD
