Metadata-Version: 2.1
Name: undi
Version: 1.0
Summary: Muon-Nuclear Dipolar Interaction
Home-page: http://github.com/bonfus/undi
Author: Pietro Bonfa
Author-email: bonfus@gmail.com
License: GPLv3
Keywords: muSR spin nuclear
Platform: UNKNOWN
Classifier: License :: OSI Approved :: GNU General Public License v3 or later (GPLv3+)
Classifier: Programming Language :: Python :: 3 :: Only
Classifier: Operating System :: OS Independent
Classifier: Intended Audience :: Science/Research
Classifier: Topic :: Scientific/Engineering :: Physics
Requires-Dist: numpy
Requires-Dist: qutip
Requires-Dist: mendeleev
